Smart_Mirror-1.7.1.dist-info/METADATA
Smart_Mirror-1.7.1.dist-info/RECORD
Smart_Mirror-1.7.1.dist-info/WHEEL
Smart_Mirror-1.7.1.dist-info/entry_points.txt
Smart_Mirror-1.7.1.dist-info/top_level.txt
smart_mirror/__init__.py
smart_mirror/__main__.py
smart_mirror/app.py
smart_mirror/myspeech.wav
smart_mirror/pywit.py
smart_mirror/recorder.py
smart_mirror/zomato.py
smart_mirror/__pycache__/__init__.cpython-36.pyc
smart_mirror/__pycache__/__main__.cpython-36.pyc
smart_mirror/__pycache__/app.cpython-36.pyc
smart_mirror/__pycache__/pywit.cpython-36.pyc
smart_mirror/__pycache__/recorder.cpython-36.pyc
smart_mirror/__pycache__/zomato.cpython-36.pyc
smart_mirror/static/.DS_Store
smart_mirror/static/assets/css/styles.min.css
smart_mirror/static/assets/js/script.min.js
smart_mirror/static/css/calendar.css
smart_mirror/static/css/time.css
smart_mirror/static/images/.DS_Store
smart_mirror/static/images/weather/.DS_Store
smart_mirror/static/images/weather/1057820-weather.zip
smart_mirror/static/images/weather/803516-weather.zip
smart_mirror/static/images/weather/eps/001-palm-tree.eps
smart_mirror/static/images/weather/eps/002-winter.eps
smart_mirror/static/images/weather/eps/003-leaf.eps
smart_mirror/static/images/weather/eps/004-icy.eps
smart_mirror/static/images/weather/eps/005-humidity.eps
smart_mirror/static/images/weather/eps/006-spring.eps
smart_mirror/static/images/weather/eps/007-autumn.eps
smart_mirror/static/images/weather/eps/008-north-2.eps
smart_mirror/static/images/weather/eps/009-west.eps
smart_mirror/static/images/weather/eps/010-south-2.eps
smart_mirror/static/images/weather/eps/011-south-1.eps
smart_mirror/static/images/weather/eps/012-south.eps
smart_mirror/static/images/weather/eps/013-east.eps
smart_mirror/static/images/weather/eps/014-north-1.eps
smart_mirror/static/images/weather/eps/015-north.eps
smart_mirror/static/images/weather/eps/016-snow-1.eps
smart_mirror/static/images/weather/eps/017-haze.eps
smart_mirror/static/images/weather/eps/018-fog-1.eps
smart_mirror/static/images/weather/eps/019-tornado.eps
smart_mirror/static/images/weather/eps/020-raindrop.eps
