Metadata-Version: 2.1
Name: Smart-Mirror
Version: 1.7.1
Summary: Smart Mirror Project
Home-page: http://katta.xyz/SmartMirror/
Author: Kushal Katta
Author-email: kushal@katta.xyz
License: UNKNOWN
Project-URL: Source Code, https://github.com/KushalKatta/SmartMirror
Keywords: smart mirror intelligent system home automation
Platform: UNKNOWN
Requires-Dist: altgraph (==0.16.1)
Requires-Dist: asn1crypto (==0.24.0)
Requires-Dist: astroid (==2.0.4)
Requires-Dist: beautifulsoup4 (==4.6.3)
Requires-Dist: bs4 (==0.0.1)
Requires-Dist: certifi (==2018.8.24)
Requires-Dist: cffi (==1.11.5)
Requires-Dist: chardet (==3.0.4)
Requires-Dist: click (==6.7)
Requires-Dist: cryptography (==2.3.1)
Requires-Dist: decorator (==4.3.0)
Requires-Dist: Flask (==1.0.2)
Requires-Dist: Flask-SocketIO (==3.0.2)
Requires-Dist: future (==0.16.0)
Requires-Dist: geocoder (==1.38.1)
Requires-Dist: gnewsclient (==1.1.0)
Requires-Dist: html5lib (==1.0.1)
Requires-Dist: idna (==2.7)
Requires-Dist: isort (==4.3.4)
Requires-Dist: itsdangerous (==0.24)
Requires-Dist: Jinja2 (==2.10)
Requires-Dist: lazy-object-proxy (==1.3.1)
Requires-Dist: macholib (==1.11)
Requires-Dist: MarkupSafe (==1.0)
Requires-Dist: mccabe (==0.6.1)
Requires-Dist: pefile (==2018.8.8)
Requires-Dist: pkginfo (==1.4.2)
Requires-Dist: prompt-toolkit (==2.0.4)
Requires-Dist: PyAudio (==0.2.11)
Requires-Dist: pycparser (==2.18)
Requires-Dist: PyFladesk (==1.0)
Requires-Dist: PyInstaller (==3.3.1)
Requires-Dist: pylint (==2.1.1)
Requires-Dist: pyOpenSSL (==18.0.0)
Requires-Dist: python-engineio (==2.2.0)
Requires-Dist: python-socketio (==2.0.0)
Requires-Dist: ratelim (==0.1.6)
Requires-Dist: requests (==2.19.1)
Requires-Dist: requests-toolbelt (==0.8.0)
Requires-Dist: rope (==0.11.0)
Requires-Dist: sip (==4.19.8)
Requires-Dist: six (==1.11.0)
Requires-Dist: Smart-Mirror (==1.4)
Requires-Dist: socketIO-client (==0.7.2)
Requires-Dist: tqdm (==4.25.0)
Requires-Dist: twine (==1.11.0)
Requires-Dist: typed-ast (==1.1.0)
Requires-Dist: urllib3 (==1.23)
Requires-Dist: wcwidth (==0.1.7)
Requires-Dist: weather-api (==1.0.4)
Requires-Dist: webencodings (==0.5.1)
Requires-Dist: websocket-client (==0.53.0)
Requires-Dist: Werkzeug (==0.14.1)
Requires-Dist: wit (==5.1.0)
Requires-Dist: wrapt (==1.10.11)
